{
    "boxShadow": "{{appsmith.theme.boxShadow.appBoxShadow}}",
    "borderColor": "#E0DEDE",
    "isVisibleDownload": true,
    "iconSVG": "/static/media/icon.e6911f8bb94dc6c4a102a74740c41763.svg",
    "topRow": 20,
    "isSortable": true,
    "type": "TABLE_WIDGET_V2",
    "inlineEditingSaveOption": "ROW_LEVEL",
    "animateLoading": true,
    "dynamicBindingPathList": [
        {"key": "accentColor"},
        {"key": "borderRadius"},
        {"key": "boxShadow"},
        {"key": "tableData"},
        {"key": "primaryColumns.Industry_Preference.computedValue"},
        {"key": "primaryColumns.Name.computedValue"},
        {"key": "primaryColumns.PortfolioSize.computedValue"},
        {"key": "primaryColumns.VCID.computedValue"}
    ],
    "needsHeightForContent": true,
    "leftColumn": 33,
    "delimiter": ",",
    "defaultSelectedRowIndex": 0,
    "showInlineEditingOptionDropdown": true,
    "flexVerticalAlignment": "start",
    "accentColor": "{{appsmith.theme.colors.primaryColor}}",
    "isVisibleFilters": false,
    "isVisible": true,
    "enableClientSideSearch": true,
    "version": 2,
    "totalRecordsCount": 0,
    "tags": [
        "Suggested",
        "Display"
    ],
    "isLoading": false,
    "childStylesheet": {
        "button": {
            "boxShadow": "none",
            "borderRadius": "{{appsmith.theme.borderRadius.appBorderRadius}}",
            "buttonColor": "{{appsmith.theme.colors.primaryColor}}"
        },
        "iconButton": {
            "boxShadow": "none",
            "borderRadius": "{{appsmith.theme.borderRadius.appBorderRadius}}",
            "buttonColor": "{{appsmith.theme.colors.primaryColor}}"
        },
        "menuButton": {
            "boxShadow": "none",
            "borderRadius": "{{appsmith.theme.borderRadius.appBorderRadius}}",
            "menuColor": "{{appsmith.theme.colors.primaryColor}}"
        },
        "editActions": {
            "saveButtonColor": "{{appsmith.theme.colors.primaryColor}}",
            "saveBorderRadius": "{{appsmith.theme.borderRadius.appBorderRadius}}",
            "discardBorderRadius": "{{appsmith.theme.borderRadius.appBorderRadius}}",
            "discardButtonColor": "{{appsmith.theme.colors.primaryColor}}"
        }
    },
    "borderRadius": "{{appsmith.theme.borderRadius.appBorderRadius}}",
    "columnUpdatedAt": 1713376165621,
    "originalBottomRow": 73,
    "primaryColumnId": "VCID",
    "defaultSelectedRowIndices": [0],
    "needsErrorInfo": false,
    "mobileBottomRow": 37,
    "widgetName": "VC_Profile",
    "defaultPageSize": 0,
    "columnOrder": [
        "Industry_Preference",
        "Name",
        "PortfolioSize",
        "VCID"
    ],
    "dynamicPropertyPathList": [],
    "displayName": "Table",
    "bottomRow": 73,
    "columnWidthMap": {},
    "parentRowSpace": 10,
    "hideCard": false,
    "mobileRightColumn": 64,
    "parentColumnSpace": 15.39794921875,
    "dynamicTriggerPathList": [],
    "borderWidth": "1",
    "primaryColumns": {
        "VCID": {
            "computedValue": "{{VC_Profile.processedTableData.map((currentRow, currentIndex) => ( currentRow[\"VCID\"]))}}",
            "isEditable": false,
            "notation": "standard",
            "alias": "VCID",
            "enableSort": true,
            "isSaveVisible": true,
            "id": "VCID",
            "isDisabled": false,
            "allowSameOptionsInNewRow": true,
            "validation": {},
            "isCellVisible": true,
            "isDerived": false,
            "textSize": "0.875rem",
            "allowCellWrapping": false,
            "index": 3,
            "isDiscardVisible": true,
            "isVisible": true,
            "label": "VCID",
            "fontStyle": "",
            "textColor": "",
            "columnType": "number",
            "thousandSeparator": true,
            "horizontalAlignment": "LEFT",
            "isCellEditable": false,
            "decimals": 0,
            "width": 150,
            "enableFilter": true,
            "sticky": "",
            "originalId": "VCID",
            "currencyCode": "USD",
            "cellBackground": "",
            "verticalAlignment": "CENTER"
        },
        "PortfolioSize": {
            "computedValue": "{{VC_Profile.processedTableData.map((currentRow, currentIndex) => ( currentRow[\"PortfolioSize\"]))}}",
            "isEditable": false,
            "notation": "standard",
            "alias": "PortfolioSize",
            "enableSort": true,
            "isSaveVisible": true,
            "id": "PortfolioSize",
            "isDisabled": false,
            "allowSameOptionsInNewRow": true,
            "validation": {},
            "isCellVisible": true,
            "isDerived": false,
            "textSize": "0.875rem",
            "allowCellWrapping": false,
            "index": 2,
            "isDiscardVisible": true,
            "isVisible": true,
            "label": "PortfolioSize",
            "fontStyle": "",
            "textColor": "",
            "columnType": "number",
            "thousandSeparator": true,
            "horizontalAlignment": "LEFT",
            "isCellEditable": false,
            "decimals": 0,
            "width": 150,
            "enableFilter": true,
            "sticky": "",
            "originalId": "PortfolioSize",
            "currencyCode": "USD",
            "cellBackground": "",
            "verticalAlignment": "CENTER"
        },
        "Industry_Preference": {
            "computedValue": "{{VC_Profile.processedTableData.map((currentRow, currentIndex) => ( currentRow[\"Industry_Preference\"]))}}",
            "isEditable": false,
            "notation": "standard",
            "alias": "Industry_Preference",
            "enableSort": true,
            "isSaveVisible": true,
            "id": "Industry_Preference",
            "isDisabled": false,
            "allowSameOptionsInNewRow": true,
            "validation": {},
            "isCellVisible": true,
            "isDerived": false,
            "textSize": "0.875rem",
            "allowCellWrapping": false,
            "index": 0,
            "isDiscardVisible": true,
            "isVisible": true,
            "label": "Industry_Preference",
            "fontStyle": "",
            "textColor": "",
            "columnType": "text",
            "thousandSeparator": true,
            "horizontalAlignment": "LEFT",
            "isCellEditable": false,
            "decimals": 0,
            "width": 150,
            "enableFilter": true,
            "sticky": "",
            "originalId": "Industry_Preference",
            "currencyCode": "USD",
            "cellBackground": "",
            "verticalAlignment": "CENTER"
        },
        "Name": {
            "computedValue": "{{VC_Profile.processedTableData.map((currentRow, currentIndex) => ( currentRow[\"Name\"]))}}",
            "isEditable": false,
            "notation": "standard",
            "alias": "Name",
            "enableSort": true,
            "isSaveVisible": true,
            "id": "Name",
            "isDisabled": false,
            "allowSameOptionsInNewRow": true,
            "validation": {},
            "isCellVisible": true,
            "isDerived": false,
            "textSize": "0.875rem",
            "allowCellWrapping": false,
            "index": 1,
            "isDiscardVisible": true,
            "isVisible": true,
            "label": "Name",
            "fontStyle": "",
            "textColor": "",
            "columnType": "text",
            "thousandSeparator": true,
            "horizontalAlignment": "LEFT",
            "isCellEditable": false,
            "decimals": 0,
            "width": 150,
            "enableFilter": true,
            "sticky": "",
            "originalId": "Name",
            "currencyCode": "USD",
            "cellBackground": "",
            "verticalAlignment": "CENTER"
        }
    },
    "key": "linypr1yi9",
    "canFreezeColumn": true,
    "isDeprecated": false,
    "rightColumn": 63,
    "textSize": "0.875rem",
    "widgetId": "p7787ss57z",
    "minWidth": 450,
    "tableData": "{{getVCbyID.data}}",
    "label": "Data",
    "searchKey": "",
    "parentId": "ddx41jf2zr",
    "renderMode": "CANVAS",
    "mobileTopRow": 9,
    "horizontalAlignment": "LEFT",
    "isVisibleSearch": false,
    "responsiveBehavior": "fill",
    "originalTopRow": 20,
    "mobileLeftColumn": 30,
    "isVisiblePagination": false,
    "verticalAlignment": "CENTER"
}